{
  "question": "The primary key is a combination of several columns of text type that provides better performance than a single-column numeric key.",
  "numberOfComments": 1,
  "answers": [
    {
      "answer": "Yes",
      "correct": false
    },
    {
      "answer": "No",
      "correct": true
    }
  ],
  "comments": [
    {
      "author": "Samuele Milan",
      "comment": "In most cases, the greatest performance is provided by a single (large) number key.",
      "date": "02-09-2023 00:00:00"
    }
  ],
  "contributors": [
    "Samuele Milan"
  ],
  "id": "1d59141c-9acf-407e-bfee-bdea1a38daf5",
  "createdAt": 1691363367006
}