{
  "question": "The impedance mismatch does not occur when you create a system entirely on the database side.",
  "numberOfComments": 1,
  "answers": [
    {
      "answer": "Yes",
      "correct": true
    },
    {
      "answer": "No",
      "correct": false
    }
  ],
  "comments": [
    {
      "author": "Samuele Milan",
      "comment": "Actually, when dealing with only one model, there is no impedance mismatch.",
      "date": "02-09-2023 00:00:00"
    }
  ],
  "contributors": [
    "Samuele Milan"
  ],
  "id": "55d3f8b9-ad86-4d58-962c-fb56957cf063",
  "createdAt": 1691363367006
}