{
  "$schema": "schemas/subject.json",
  "title": "Fizyka k2",
  "id": "fizk2",
  "data": [
    {
      "question": "&nbsp;<p></p>\n<p><span>Niezmiennikiem transformacji Lorentza zastosowanej w teorii względności Einsteina&nbsp;jest</span>\n          </p>",
      "id": 2313,
      "numberOfComments": 0,
      "answers": [
        {
          "answer": "&nbsp;<p></p>\n<p><span>absolutny układ odniesienia</span></p>",
          "correct": false
        },
        {
          "answer": "&nbsp;<p></p>\n<p><span>prędkość poruszającego się obserwatora</span></p>",
          "correct": false
        },
        {
          "answer": "&nbsp;<p></p>\n<p><span>prędkość światła</span></p>",
          "correct": true
        }
      ],
      "comments": []
    },
    {
      "question": "&nbsp;<p></p>\n<p><span>W mechanice kwantowej,&nbsp;gdy energia cząstki jest mniejsza od bariery potencjału, prawdopodobieństwo, że cząstka tę barierę pokona</span>\n          </p>",
      "id": 2314,
      "numberOfComments": 0,
      "answers": [
        {
          "answer": "&nbsp;<p></p>\n<p><span>jest skończone</span></p>",
          "correct": true
        },
        {
          "answer": "&nbsp;<p></p>\n<p><span>jest mniejsze od zera</span></p>",
          "correct": false
        },
        {
          "answer": "&nbsp;<p></p>\n<p><span>jest większe od jedności</span></p>",
          "correct": false
        }
      ],
      "comments": []
    },
    {
      "question": "&nbsp;<p></p>\n<p><span>Doświadczenie Sterna-Gerlacha dowiodzi, że</span>\n          </p>",
      "id": 2315,
      "numberOfComments": 0,
      "answers": [
        {
          "answer": "&nbsp;<p></p>\n<p><span>składowa momentu magnetycznego atomu w kierunku zewnętrznego pola magnetycznego przyjmuje wartości dyskretne</span></p>",
          "correct": true
        },
        {
          "answer": "&nbsp;<p></p>\n<p><span>składowa momentu magnetycznego atomu w kierunku zewnętrznego pola magnetycznego przyjmuje wartości ciągłe</span></p>",
          "correct": false
        },
        {
          "answer": "&nbsp;<p></p>\n<p><span>spiny elektronów mogą mieć tylko wartości całkowite</span></p>",
          "correct": false
        }
      ],
      "comments": []
    },
    {
      "question": "&nbsp;<p></p>\n<p><span lang=\"EN-US\">As a pulse travels though a uniform medium, the speed of the pulse</span>\n          </p>",
      "id": 2316,
      "numberOfComments": 0,
      "answers": [
        {
          "answer": "&nbsp;<p></p>\n<p><span>increases</span></p>",
          "correct": false
        },
        {
          "answer": "&nbsp;<p></p>\n<p><span>remains the same</span></p>",
          "correct": false
        },
        {
          "answer": "&nbsp;<p></p>\n<p><span>decreases <br></span></p>",
          "correct": true
        }
      ],
      "comments": []
    },
    {
      "question": "&nbsp;<p></p>\n<p><span>Pojęcie 'fali materii' wprowadził do fizyki w roku 1924</span>\n          </p>",
      "id": 2317,
      "numberOfComments": 0,
      "answers": [
        {
          "answer": "&nbsp;<p></p>\n<p><span>Mikołaj Kopernik</span></p>",
          "correct": false
        },
        {
          "answer": "&nbsp;<p></p>\n<p><span>Izaak Newton</span></p>",
          "correct": false
        },
        {
          "answer": "&nbsp;<p></p>\n<p><span>Louis de Broglie</span></p>",
          "correct": true
        }
      ],
      "comments": []
    },
    {
      "question": "&nbsp;<p></p>\n<p><span>W teorii względności Einsteina pręt ma największą długość w układzie odniesienia</span>\n          </p>",
      "id": 2318,
      "numberOfComments": 0,
      "answers": [
        {
          "answer": "&nbsp;<p></p>\n<p><span>i w układzie odniesienia względem którego spoczywa i względem którego jest w ruchu i długość ta zawsze jest taka sama</span></p>",
          "correct": false
        },
        {
          "answer": "&nbsp;<p></p>\n<p><span>względem którego się porusza</span></p>",
          "correct": false
        },
        {
          "answer": "&nbsp;<p></p>\n<p><span>w którym spoczywa</span></p>",
          "correct": true
        }
      ],
      "comments": []
    },
    {
      "question": "&nbsp;<p></p>\n<p><span>Na skraju niewielkiego krążka obracającego się swobodnie, siedzi żuczek. W pewnej chwili żuczek zaczyna iść ku środkowi krążka. Czy prędkość kątowa żuczka i krążka:</span>\n          </p>",
      "id": 2319,
      "numberOfComments": 0,
      "answers": [
        {
          "answer": "&nbsp;<p></p>\n<p><span>zmaleje</span></p>",
          "correct": false
        },
        {
          "answer": "&nbsp;<p></p>\n<p><span>wzrośnie</span></p>",
          "correct": false
        },
        {
          "answer": "&nbsp;<p></p>\n<p><span>pozostanie bez zmian</span></p>",
          "correct": true
        }
      ],
      "comments": []
    },
    {
      "question": "&nbsp;<p></p>\n<p><span>Podczas mroĽnego dnia gorąca woda (~80C</span><span>)</span>\n          </p>",
      "id": 2320,
      "numberOfComments": 0,
      "answers": [
        {
          "answer": "&nbsp;<p></p>\n<p><span>i ciepła woda (</span><span>C) zamarzają jednakowo szybko</span></p>",
          "correct": false
        },
        {
          "answer": "&nbsp;<p></p>\n<p><span>zamarza wolniej niż ciepła (</span><span>C)</span></p>",
          "correct": true
        },
        {
          "answer": "&nbsp;<p></p>\n<p><span>zamarza szybciej niż ciepła (</span><span>C)</span></p>",
          "correct": false
        }
      ],
      "comments": []
    },
    {
      "question": "&nbsp;<p></p>\n<p><span>Elektryczny ładunek elementarny e ma wartość</span>\n          </p>",
      "id": 2321,
      "numberOfComments": 0,
      "answers": [
        {
          "answer": "&nbsp;<p></p>\n<p><span>1,6021892*10^-17 C</span></p>",
          "correct": false
        },
        {
          "answer": "<span>1,6021892*10^19 C</span>",
          "correct": false
        },
        {
          "answer": "<span>1,6021892*10^-19 C</span>",
          "correct": true
        }
      ],
      "comments": []
    },
    {
      "question": "&nbsp;<p></p>\n<p><span>Dzięki zjawisku tunelowemu</span>\n          </p>",
      "id": 2322,
      "numberOfComments": 0,
      "answers": [
        {
          "answer": "&nbsp;<p></p>\n<p><span>może zachodzic fuzja jądrowa, np.&nbsp; wewnątrz gwiazd, wytwarzając olbrzymie ilości energii</span></p>",
          "correct": true
        },
        {
          "answer": "&nbsp;<p></p>\n<p><span>na przykład szybciej zbudować metro w Warszawie</span></p>",
          "correct": false
        },
        {
          "answer": "&nbsp;<p></p>\n<p><span>można było zbudować skaningowy mikroskop tunelowy (STM - scanning tunneling microscope) pozwalający badać powierzchnie materiałów w skali pojedynczych atomów</span></p>",
          "correct": true
        }
      ],
      "comments": []
    },
    {
      "question": "&nbsp;<p></p>\n<p><span>Istotę zjawiska fotoelektrycznego wytłumaczył w roku 1904</span>\n          </p>",
      "id": 2323,
      "numberOfComments": 0,
      "answers": [
        {
          "answer": "&nbsp;<p></p>\n<p><span>Albert Einstein</span></p>",
          "correct": true
        },
        {
          "answer": "<p>&nbsp;</p>\n<table class=\"MsoNormalTable\" width=\"100%\" border=\"0\" cellpadding=\"0\">\n<tbody>\n<tr>\n<td>\n<p class=\"MsoNormal\"><span>Wilhelm Conrad Röntgen</span></p>\n</td>\n</tr>\n</tbody>\n</table>",
          "correct": false
        },
        {
          "answer": "&nbsp;<p></p>\n<p><span>Max Planck</span></p>",
          "correct": false
        }
      ],
      "comments": []
    },
    {
      "question": "&nbsp;<p></p>\n<p><span>Liczba możliwych typów sieci Bravais wynosi:</span>\n          </p>",
      "id": 2324,
      "numberOfComments": 0,
      "answers": [
        {
          "answer": "<p><span>15</span></p>",
          "correct": false
        },
        {
          "answer": "&nbsp;<p></p>\n<p><span>14</span></p>",
          "correct": true
        },
        {
          "answer": "&nbsp;<p></p>\n<p><span>9</span></p>",
          "correct": false
        }
      ],
      "comments": []
    },
    {
      "question": "&nbsp;<p></p>\n<p><span>Doświadczenie Michelsona-Morleya dotyczyło</span>\n          </p>",
      "id": 2325,
      "numberOfComments": 0,
      "answers": [
        {
          "answer": "&nbsp;<p></p>\n<p><span>zjawiska stroboskopowego</span></p>",
          "correct": false
        },
        {
          "answer": "&nbsp;<p></p>\n<p><span>wpływu ruchu Ziemi na prędkość światła</span></p>",
          "correct": true
        },
        {
          "answer": "&nbsp;<p></p>\n<p><span>pomiaru bezwzględnej prędkości światła w próżni</span></p>",
          "correct": false
        }
      ],
      "comments": []
    },
    {
      "question": "&nbsp;<p></p>\n<p><span>Sieć Bravais, to</span>\n          </p>",
      "id": 2326,
      "numberOfComments": 0,
      "answers": [
        {
          "answer": "&nbsp;<p></p>\n<p><span>zespół sieci intranetowych podłączonych łącznie do sieci miejskiej</span></p>",
          "correct": false
        },
        {
          "answer": "&nbsp;<p></p>\n<p><span>możliwy sposób upakowania atomów w krysztale</span></p>",
          "correct": true
        },
        {
          "answer": "&nbsp;<p></p>\n<p><span>sposób wiązania atomów w cząsteczki</span></p>",
          "correct": false
        }
      ],
      "comments": []
    },
    {
      "question": "&nbsp;<p></p>\n<p><span>Próbkę żelaza poddano procesowi rdzewienia. Masa tej próbki</span>\n          </p>",
      "id": 2327,
      "numberOfComments": 0,
      "answers": [
        {
          "answer": "&nbsp;<p></p>\n<p><span>zwiększy się</span></p>",
          "correct": true
        },
        {
          "answer": "&nbsp;<p></p>\n<p><span>zmniejszy się</span></p>",
          "correct": false
        },
        {
          "answer": "&nbsp;<p></p>\n<p><span>zmniejszy się, ale tylko nieznacznie</span></p>",
          "correct": false
        }
      ],
      "comments": []
    },
    {
      "question": "W węźle sieci krystalicznej może znajdować się",
      "id": 2328,
      "numberOfComments": 0,
      "answers": [
        {
          "answer": "tylko&nbsp;trzy atomy",
          "correct": false
        },
        {
          "answer": "bardzo dużo atomów, nawet 10^4",
          "correct": true
        },
        {
          "answer": "tylko jeden atom",
          "correct": false
        }
      ],
      "comments": []
    },
    {
      "question": "&nbsp;<p></p>\n<p><span>Komórka elementarna sześciennej sieci krystalicznej może być typu</span>\n          </p>",
      "id": 2329,
      "numberOfComments": 0,
      "answers": [
        {
          "answer": "&nbsp;<p></p>\n<p><span>bcc - body centered cubic (centrowana objętościowo)</span></p>",
          "correct": true
        },
        {
          "answer": "&nbsp;<p></p>\n<p><span>fcc - face centered cubic (centrowana powierzchniowo)</span></p>",
          "correct": true
        },
        {
          "answer": "&nbsp;<p></p>\n<p><span>bfcc - body and face centered cubic (centrowana objętościowo i powierzchniowo)</span></p>",
          "correct": false
        }
      ],
      "comments": []
    },
    {
      "question": "&nbsp;<p></p>\n<p><span>W teorii względności Einsteina wszystkie prawa fizyczne są niezmiennicze względem transformacji</span>\n          </p>",
      "id": 2330,
      "numberOfComments": 0,
      "answers": [
        {
          "answer": "&nbsp;<p></p>\n<p><span>Ostrogradzkiego</span></p>",
          "correct": false
        },
        {
          "answer": "&nbsp;<p></p>\n<p><span>Galileusza</span></p>",
          "correct": false
        },
        {
          "answer": "&nbsp;<p></p>\n<p><span>Lorentza</span></p>",
          "correct": true
        }
      ],
      "comments": []
    },
    {
      "question": "&nbsp;<p></p>\n<p><span>Jednostką ładunku elektrycznego w systemie SI jest:</span>\n          </p>",
      "id": 2331,
      "numberOfComments": 0,
      "answers": [
        {
          "answer": "&nbsp;<p></p>\n<p><span>elementarny ładunek elektryczny [e]</span></p>",
          "correct": false
        },
        {
          "answer": "<p>&nbsp;</p>\n<table class=\"MsoNormalTable\" width=\"100%\" border=\"0\" cellpadding=\"0\">\n<tbody>\n<tr>\n<td>\n<p class=\"MsoNormal\"><span>1 Coulomb [C]</span></p>\n</td>\n</tr>\n</tbody>\n</table>",
          "correct": false
        },
        {
          "answer": "&nbsp;<p></p>\n<p><span>1 Amper [A]</span></p>",
          "correct": false
        }
      ],
      "comments": []
    },
    {
      "question": "W teorii względności Einsteina odstępy czasu delta t w układzie odniesienia nieruchomym, są dla obserwatora ruchomego",
      "id": 2332,
      "numberOfComments": 0,
      "answers": [
        {
          "answer": "wydłużone",
          "correct": true
        },
        {
          "answer": "skrócone",
          "correct": false
        },
        {
          "answer": "identyczne jak w układzie nieruchomym",
          "correct": false
        }
      ],
      "comments": []
    },
    {
      "question": "&nbsp;<p></p>\n<p><span>Na wysokości 1000 km nad Ziemią wystrzelono pocisk z prędkością V = 1000 m/s prostopadłą do natężenia pola grawitacyjnego. Proszę przyjąć brak tarcia oraz potraktować Ziemię i pocisk jako punkty materialne. Torem pocisku będzie:</span>\n          </p>",
      "id": 2333,
      "numberOfComments": 0,
      "answers": [
        {
          "answer": "&nbsp;<p></p>\n<p><span>hiperbola</span></p>",
          "correct": false
        },
        {
          "answer": "&nbsp;<p></p>\n<p><span>elipsa</span></p>",
          "correct": false
        },
        {
          "answer": "&nbsp;<p></p>\n<p><span>parabola</span></p>",
          "correct": true
        }
      ],
      "comments": []
    },
    {
      "question": "&nbsp;<p></p>\n<p><span>W punkcie leżącym w połowie odległości pomiędzy dwoma różnoimiennymi ładunkami elektrycznymi ale o jednakowych wartościach</span>\n          </p>",
      "id": 2334,
      "numberOfComments": 0,
      "answers": [
        {
          "answer": "&nbsp;<p></p>\n<p><span>tylko natężenie pola elektrostatycznego jest równe zero</span></p>",
          "correct": false
        },
        {
          "answer": "&nbsp;<p></p>\n<p><span>zarówno potencjał elektrostatyczny jak i natężenie pola elektrostatycznego są równe zeru</span></p>",
          "correct": true
        },
        {
          "answer": "&nbsp;<p></p>\n<p><span>zarówno potencjał elektrostatyczny jak i natężenie pola elektrostatycznego są różne od zera</span></p>",
          "correct": false
        }
      ],
      "comments": []
    },
    {
      "question": "&nbsp;<p></p>\n<p><span>Jeden z postaulatów Bohra dotyczący budowy atomu stwierdzał, że</span>\n          </p>",
      "id": 2335,
      "numberOfComments": 0,
      "answers": [
        {
          "answer": "&nbsp;<p></p>\n<p><span>istnieją orbity stacjonarne, na których elektron&nbsp; promieniuje dowolnie wielką energię</span></p>",
          "correct": false
        },
        {
          "answer": "&nbsp;<p></p>\n<p><span>istnieją orbity stacjonarne, na których elektron nie promieniuje żadnej energii, wiec jego energia pozostaje niezmieniona</span></p>",
          "correct": true
        },
        {
          "answer": "<p>&nbsp;</p>\n<table class=\"MsoNormalTable\" width=\"100%\" border=\"0\" cellpadding=\"0\">\n<tbody>\n<tr>\n<td>\n<p class=\"MsoNormal\"><span>istnieja orbity stacjonarne, na których elektron promieniuje energię tylko sposób ciągły, a nie kwantami</span></p>\n</td>\n</tr>\n</tbody>\n</table>",
          "correct": false
        }
      ],
      "comments": []
    },
    {
      "question": "&nbsp;<p></p>\n<p><span>Wewnątrz gwiazdy duża część materii jest zjonizowana. Większość masy gwiazdy to swobodne protony. Dwa takie protony, znajdujące się początkowo w niewielkiej odległości od siebie, będą pod wpływem elektrycznych sił wzajemnego oddziaływania:</span>\n          </p>",
      "id": 2336,
      "numberOfComments": 0,
      "answers": [
        {
          "answer": "&nbsp;<p></p>\n<p><span>oddalać się od siebie ruchem jednostajnym</span></p>",
          "correct": false
        },
        {
          "answer": "&nbsp;<p></p>\n<p><span>oddalać się od siebie ruchem jednostajnie przyspieszonym (ze stałym przyspieszeniem)</span></p>",
          "correct": false
        },
        {
          "answer": "&nbsp;<p></p>\n<p><span>oddalać się od siebie ruchem niejednostajnie przyspieszonym z malejącym przyspieszeniem</span></p>",
          "correct": true
        }
      ],
      "comments": []
    },
    {
      "question": "&nbsp;<p></p>\n<p><span>Powietrze w oponie wystawionej na działanie promieni słonecznych ulega nagrzaniu. Przyjmując, że objętość opony nie uległa zmianie, możemy powiedzieć, że energia wewnętrzna powietrza w oponie:</span>\n          </p>",
      "id": 2337,
      "numberOfComments": 0,
      "answers": [
        {
          "answer": "&nbsp;<p></p>\n<p><span>wzrosła, a powietrze nie wykonało pracy</span></p>",
          "correct": true
        },
        {
          "answer": "<p>&nbsp;</p>\n<table class=\"MsoNormalTable\" width=\"100%\" border=\"0\" cellpadding=\"0\">\n<tbody>\n<tr>\n<td>\n<p class=\"MsoNormal\"><span>zmalała, bo powietrze wykonało pracę</span></p>\n</td>\n</tr>\n</tbody>\n</table>",
          "correct": false
        },
        {
          "answer": "<p>&nbsp;</p>\n<table class=\"MsoNormalTable\" width=\"100%\" border=\"0\" cellpadding=\"0\">\n<tbody>\n<tr>\n<td>\n<p class=\"MsoNormal\"><span>wzrosła, bo powietrze wykonało pracę</span></p>\n</td>\n</tr>\n</tbody>\n</table>",
          "correct": false
        }
      ],
      "comments": []
    },
    {
      "question": "&nbsp;<p></p>\n<p><span>Jednostką natężenia prądu elektrycznego jest</span>\n          </p>",
      "id": 2338,
      "numberOfComments": 0,
      "answers": [
        {
          "answer": "&nbsp;<p></p>\n<p><span>1 V = 1 C/s</span></p>",
          "correct": false
        },
        {
          "answer": "<p>&nbsp;</p>\n<table class=\"MsoNormalTable\" width=\"100%\" border=\"0\" cellpadding=\"0\">\n<tbody>\n<tr>\n<td>\n<p class=\"MsoNormal\"><span>1 omega = 10^5 ładunków elementarnych na minutę</span></p>\n</td>\n</tr>\n</tbody>\n</table>",
          "correct": false
        },
        {
          "answer": "&nbsp;<p></p>\n<p><span>1 A = 1 C/s</span></p>",
          "correct": true
        }
      ],
      "comments": []
    },
    {
      "question": "&nbsp;<p></p>\n<p><span>Energia cieplna dociera ze Słońca do satelity geostacjonarnego krążącego po orbicie dzięki:</span>\n          </p>",
      "id": 2339,
      "numberOfComments": 0,
      "answers": [
        {
          "answer": "&nbsp;<p></p>\n<p><span>tylko konwekcji</span></p>",
          "correct": false
        },
        {
          "answer": "&nbsp;<p></p>\n<p><span>tylko promieniowaniu</span></p>",
          "correct": true
        },
        {
          "answer": "&nbsp;<p></p>\n<p><span>przewodnictwu i promieniowaniu</span></p>",
          "correct": false
        }
      ],
      "comments": []
    },
    {
      "question": "&nbsp;<p></p>\n<p><span>The three primary colors of light are</span>\n          </p>",
      "id": 2340,
      "numberOfComments": 0,
      "answers": [
        {
          "answer": "&nbsp;<p></p>\n<p><span>white, black, gray</span></p>",
          "correct": false
        },
        {
          "answer": "&nbsp;<p></p>\n<p><span>blue, green, yellow</span></p>",
          "correct": false
        },
        {
          "answer": "&nbsp;<p></p>\n<p><span>red, blue, green</span></p>",
          "correct": true
        }
      ],
      "comments": []
    },
    {
      "question": "&nbsp;<p></p>\n<p><span>Jeden z postaulatów Bohra dotyczący budowy atomu stwierdzał, że</span>\n          </p>",
      "id": 2341,
      "numberOfComments": 0,
      "answers": [
        {
          "answer": "&nbsp;<p></p>\n<p><span>istnieja orbity stacjonarne, na których elektron&nbsp; promieniuje energię tylko kwantami, a nie w sposób ciągły</span></p>",
          "correct": false
        },
        {
          "answer": "&nbsp;<p></p>\n<p><span>istnieja orbity stacjonarne, na których elektron promieniuje energię tylko sposób ciągły, a nie kwantami</span></p>",
          "correct": false
        },
        {
          "answer": "&nbsp;<p></p>\n<p><span>istnieją orbity stacjonarne, na których elektron nie promieniuje żadnej energii, wiec jego energia pozostaje niezmieniona</span></p>",
          "correct": true
        }
      ],
      "comments": []
    },
    {
      "question": "&nbsp;<p></p>\n<p><span>Pierwszy krok, umożliwiający w perspektywie wyjaśnienie<br> sprzeczności w widmie promieniowania ciała doskonale czarnego wprowadzjąc pojęcie kwantu energii, zrobił w 1900 r.</span>\n          </p>",
      "id": 2342,
      "numberOfComments": 0,
      "answers": [
        {
          "answer": "&nbsp;<p></p>\n<p><span>Albert Einstein</span></p>",
          "correct": false
        },
        {
          "answer": "&nbsp;<p></p>\n<p><span>Max Planck</span></p>",
          "correct": true
        },
        {
          "answer": "&nbsp;<p></p>\n<p><span>Marian Smoluchowski</span></p>",
          "correct": false
        }
      ],
      "comments": []
    },
    {
      "question": "&nbsp;<p></p>\n<p><span>Na ekranie pracującego telewizora (z lampą kineskopową), osadza się kurz. Zjawisko to spowodowane jest:</span>\n          </p>",
      "id": 2343,
      "numberOfComments": 0,
      "answers": [
        {
          "answer": "&nbsp;<p></p>\n<p><span>zwiększonym przewodnictwem monitora</span></p>",
          "correct": false
        },
        {
          "answer": "&nbsp;<p></p>\n<p><span>promieniowaniem monitora</span></p>",
          "correct": false
        },
        {
          "answer": "&nbsp;<p></p>\n<p><span>elektryzowaniem się monitora</span></p>",
          "correct": true
        }
      ],
      "comments": []
    },
    {
      "question": "&nbsp;<p></p>\n<p><span>Which of the following statements are true about power?</span>\n          </p>",
      "id": 2344,
      "numberOfComments": 0,
      "answers": [
        {
          "answer": "&nbsp;<p></p>\n<p><span>Power refers to how fast work is done upon an object</span></p>",
          "correct": true
        },
        {
          "answer": "&nbsp;<p></p>\n<p><span>Powerful people or powerful machines are simply people or machines which always do a lot of work.</span></p>",
          "correct": false
        },
        {
          "answer": "&nbsp;<p></p>\n<p>&nbsp;</p>\n<p><span>If person A and person B do the same job but person B does it faster, then person A does more work but person B has more power.</span></p>",
          "correct": false
        },
        {
          "answer": "&nbsp;<p></p>\n<p><span><br></span></p>",
          "correct": false
        }
      ],
      "comments": []
    },
    {
      "question": "&nbsp;<p></p>\n<p><span>Wartość stałej Plancka h(coś podobnego do h) wynosi<br></span>\n          </p>",
      "id": 2345,
      "numberOfComments": 0,
      "answers": [
        {
          "answer": "h = h/2 pi = 1,054887 * 10^34 J s",
          "correct": false
        },
        {
          "answer": "h = h/2 pi = 1,054887 * 10^-27 erg s",
          "correct": true
        },
        {
          "answer": "h = h/2 pi = 1,054887 * 10^-72 erg s",
          "correct": false
        }
      ],
      "comments": []
    },
    {
      "question": "&nbsp;<p></p>\n<p><span>Funkcja falowa&nbsp;psi(trójząb xD) występująca w równaniu Schrödingera ma następującą interpretację</span>\n          </p>",
      "id": 2346,
      "numberOfComments": 0,
      "answers": [
        {
          "answer": "<p><span>iloczyn&nbsp;psi*psi jest gęstością prawdopodobienstwa, że cząstka w danej chwili znajduje się w danym miejscu przestrzeni w pewnej infinitezymalnej objetosci&nbsp;dV (<span>psi</span> - funkcja zespolona sprzężona do&nbsp;psi)</span></p>\n\n<p>&nbsp;</p>",
          "correct": true
        },
        {
          "answer": "&nbsp;<p></p>\n<p><span>iloraz&nbsp;psi/psi jest gęstością prawdopodobienstwa, że cząstka w danej chwili znajduje się w danym miejscu przestrzeni w pewnej infinitezymalnej objetosci&nbsp;dV (psi - funkcja zespolona sprzężona do psi)</span></p>",
          "correct": false
        },
        {
          "answer": "&nbsp;<p></p>\n<p><span>jest to gęstość prawdopodobienstwa, że cząstka w danej chwili znajduje się w danym miejscu przestrzeni w pewnej infinitezymalnej objetosci dV<br></span></p>",
          "correct": false
        }
      ],
      "comments": []
    },
    {
      "question": "&nbsp;<p></p>\n<p><span>Elektron odkrył(a) w roku 1897</span>\n          </p>",
      "id": 2347,
      "numberOfComments": 0,
      "answers": [
        {
          "answer": "&nbsp;<p></p>\n<p><span>Antoine Henri Becquerel</span></p>",
          "correct": false
        },
        {
          "answer": "&nbsp;<p></p>\n<p><span>Joseph John Thomson</span></p>",
          "correct": true
        },
        {
          "answer": "&nbsp;<p></p>\n<p><span>Wilhelm Conrad Röntgen</span></p>",
          "correct": false
        }
      ],
      "comments": []
    },
    {
      "question": "&nbsp;<p></p>\n<p><span>Jednostką ładunku elektrycznego w systemie SI jest</span>\n          </p>",
      "id": 2348,
      "numberOfComments": 0,
      "answers": [
        {
          "answer": "<p>&nbsp;</p>\n<table class=\"MsoNormalTable\" width=\"100%\" border=\"0\" cellpadding=\"0\">\n<tbody>\n<tr>\n<td>\n<p class=\"MsoNormal\"><span>elementarny ładunek elektryczny [e]</span></p>\n</td>\n</tr>\n</tbody>\n</table>",
          "correct": false
        },
        {
          "answer": "&nbsp;<p></p>\n<p><span>1 Amper na 1 sekundę [A/s]</span></p>",
          "correct": true
        },
        {
          "answer": "&nbsp;<p></p>\n<p><span>1 Coulomb [C]</span></p>",
          "correct": true
        }
      ],
      "comments": []
    },
    {
      "question": "&nbsp;<p></p>\n<p><span>Równanie Schrödingera opisuje</span>\n          </p>",
      "id": 2349,
      "numberOfComments": 0,
      "answers": [
        {
          "answer": "&nbsp;<p></p>\n<p><span>fale elektromagnetyczne w ośrodku materialnym</span></p>",
          "correct": false
        },
        {
          "answer": "&nbsp;<p></p>\n<p><span>fale materii cząstek elementarnych bezspinowych</span></p>",
          "correct": true
        },
        {
          "answer": "&nbsp;<p></p>\n<p><span>fale akustyczne</span></p>",
          "correct": false
        }
      ],
      "comments": []
    },
    {
      "question": "<pre>Na skraju niewielkiego obracającego się krążka, siedzi żuczek. W pewnej chwili żuczek zaczyna ić ku rodkowi kršżka. Czy moment bezwładnoci układu żuczek-krążek:</pre>",
      "id": 2350,
      "numberOfComments": 0,
      "answers": [
        {
          "answer": "zmaleje",
          "correct": true
        },
        {
          "answer": "pozostanie bez zmian",
          "correct": false
        },
        {
          "answer": "wzrośnie",
          "correct": false
        }
      ],
      "comments": []
    },
    {
      "question": "Wartość stałęj Plancka h wynosi",
      "id": 2351,
      "numberOfComments": 0,
      "answers": [
        {
          "answer": "h = h/2 pi = 1,054887 * 10 ^ -43 J s",
          "correct": true
        },
        {
          "answer": "h = h/2 pi = 1,054887 * 10 ^ -18 J s",
          "correct": false
        },
        {
          "answer": "h = h/2 pi = 1,054887 * 10 ^ -27 erg s",
          "correct": true
        }
      ],
      "comments": []
    },
    {
      "question": "prawdopodobieństwo, że cząstka przekroczy barierę potęcjału, zależy",
      "id": 2352,
      "numberOfComments": 0,
      "answers": [
        {
          "answer": "od szerokości potencjału",
          "correct": true
        },
        {
          "answer": "od czynności eksperymentatora",
          "correct": false
        },
        {
          "answer": "od kształtu potencjału",
          "correct": false
        }
      ],
      "comments": []
    },
    {
      "question": "&nbsp;<p></p>\n<p><span>W teorii względności Einsteina odstępy czasu delta t w układzie odniesienia nieruchomym, są dla obserwatora ruchomego</span>\n          </p>",
      "id": 2353,
      "numberOfComments": 0,
      "answers": [
        {
          "answer": "wydłużone",
          "correct": true
        },
        {
          "answer": "identyczne jak w układzie ruchomym",
          "correct": false
        },
        {
          "answer": "czasami wydłużone, a czasami skrócone",
          "correct": false
        }
      ],
      "comments": []
    },
    {
      "question": "<span>Elektryczny ładunek elementarny e ma wartość</span>",
      "id": 2354,
      "numberOfComments": 0,
      "answers": [
        {
          "answer": "<span>1,6021892*10^-29 C<br></span>",
          "correct": false
        },
        {
          "answer": "<span>1,6021892*10^19 C<br></span>",
          "correct": false
        },
        {
          "answer": "<span>1,6021892*10^-19 C<br></span>",
          "correct": true
        }
      ],
      "comments": []
    },
    {
      "question": "Zmiana pędu ciała może być wywołana",
      "id": 2355,
      "numberOfComments": 0,
      "answers": [
        {
          "answer": "tylko działając na to ciało siłą",
          "correct": false
        },
        {
          "answer": "działając na to ciało siła",
          "correct": true
        },
        {
          "answer": "uderzeniem przez inne ciało",
          "correct": true
        }
      ],
      "comments": []
    },
    {
      "question": "Jednostką ładunku elektrycznego w systemie SI jest:",
      "id": 2356,
      "numberOfComments": 0,
      "answers": [
        {
          "answer": "1 Volt [V]",
          "correct": false
        },
        {
          "answer": "1 Coulomb [C]",
          "correct": true
        },
        {
          "answer": "1 Amper na 1 sekundę [A/s]",
          "correct": true
        }
      ],
      "comments": []
    },
    {
      "question": "Bohr w sym modelu atomu założył, że",
      "id": 2357,
      "numberOfComments": 0,
      "answers": [
        {
          "answer": "procesowi przejścia z jednej stacjonarnej orbity na inną stacojnarną orbitę towarzyszy emisja jednorodnego promieniowania, dla którego związek częstości v i emitowanej energii E dany jest wzorem Plancka E = h/v",
          "correct": false
        },
        {
          "answer": "procesowi przejścia z jednej stacjonarnej orbity na inną stacojnarną orbitę towarzyszy emisja jednorodnego promieniowania, dla którego związek częstości v i emitowanej energii E dany jest wzorem Plancka E =1/2h*v",
          "correct": false
        },
        {
          "answer": "procesowi przejścia z jednej stacjonarnej orbity na inną stacojnarną orbitę towarzyszy emisja jednorodnego promieniowania, dla którego związek częstości v i emitowanej energii E dany jest wzorem Plancka E = h*v",
          "correct": true
        }
      ],
      "comments": []
    },
    {
      "question": "W wężle sieci krystalicznej może znajdować się",
      "id": 2358,
      "numberOfComments": 0,
      "answers": [
        {
          "answer": "tylko trzy atomy",
          "correct": false
        },
        {
          "answer": "bardzo dużo atomów, nawet 10^4",
          "correct": true
        },
        {
          "answer": "tylko dwa atomy",
          "correct": false
        }
      ],
      "comments": []
    },
    {
      "question": "Doświadczenie Younga dawało świadectwo o",
      "id": 2359,
      "numberOfComments": 0,
      "answers": [
        {
          "answer": "korpuskularnej naturze światła",
          "correct": false
        },
        {
          "answer": "istnieniu promieniotwórczości",
          "correct": false
        },
        {
          "answer": "falowej naturze światła",
          "correct": true
        }
      ],
      "comments": []
    },
    {
      "question": "<span>Materials that don't allow electricity to flow throught them easily are called</span>",
      "id": 2360,
      "numberOfComments": 0,
      "answers": [
        {
          "answer": "<span>conductors</span>",
          "correct": false
        },
        {
          "answer": "<span>insulators</span>",
          "correct": true
        },
        {
          "answer": "<span>semiconductors</span>",
          "correct": false
        }
      ],
      "comments": []
    },
    {
      "question": "Samolot leciał najpierw 400 km na wschód, a następnie na północ. Przemieszczenie samolotu na całej trasie wyniosło 500 km. Droga przebyta przez ten samolot jest równa:",
      "id": 2361,
      "numberOfComments": 0,
      "answers": [
        {
          "answer": "700 km",
          "correct": true
        },
        {
          "answer": "800 km",
          "correct": false
        },
        {
          "answer": "900 km",
          "correct": false
        }
      ],
      "comments": []
    },
    {
      "question": "Niezmiennikiem transformacji Lorentza zastosowanej w teorii względności Einsteina&nbsp;jest",
      "id": 2362,
      "numberOfComments": 0,
      "answers": [
        {
          "answer": "prędkość poruszającego się obserwatora",
          "correct": false
        },
        {
          "answer": "prędkość fal elektromagnetycznych",
          "correct": true
        },
        {
          "answer": "absolutny układ odniesienia",
          "correct": false
        },
        {
          "answer": "prędkość światła",
          "correct": true
        }
      ],
      "comments": []
    },
    {
      "question": "Wartość stałej Plancka h wynosi",
      "id": 2363,
      "numberOfComments": 0,
      "answers": [
        {
          "answer": "h = h/2 pi = 1,054887 * 10 ^ -34 J s",
          "correct": true
        },
        {
          "answer": "h = h/2 pi = 1,054887 * 10 ^ -18 J s",
          "correct": false
        },
        {
          "answer": "h = h/2 pi = 1,054887 * 10 ^ 34 J s",
          "correct": false
        }
      ],
      "comments": []
    },
    {
      "question": "Jednostką natężenia prądu elektrycznego jest",
      "id": 2364,
      "numberOfComments": 0,
      "answers": [
        {
          "answer": "1 V = 1 C/s",
          "correct": false
        },
        {
          "answer": "1 A = 1 C/s",
          "correct": true
        },
        {
          "answer": "1 C = 1 A/s",
          "correct": false
        }
      ],
      "comments": []
    },
    {
      "question": "Częstotliwości podstawowa drgań struny obustronnie zaczepionej zależy od:",
      "id": 2365,
      "numberOfComments": 0,
      "answers": [
        {
          "answer": "liniowej gęstości masy struny",
          "correct": true
        },
        {
          "answer": "długości struny",
          "correct": true
        },
        {
          "answer": "siły napinającej strunę",
          "correct": true
        }
      ],
      "comments": []
    },
    {
      "question": "Wzór Balmera pozwala określić",
      "id": 2366,
      "numberOfComments": 0,
      "answers": [
        {
          "answer": "związek liczby atomowej z liczbą masową atomu",
          "correct": false
        },
        {
          "answer": "związek pomiędzy prędkością światła a prędkością fal akustycznych w próżni",
          "correct": false
        },
        {
          "answer": "związek między długościami fali linii widmowych atomu wodoru",
          "correct": true
        }
      ],
      "comments": []
    }
  ],
  "updatedAt": 1712174715407
}