{
  "question": "Kiedy wskazane jest użycie indeksu pogrupowanego zamiast niepogrupowanego w MS SQL Server",
  "isMarkdown": true,
  "comments": [],
  "answers": [
    {
      "answer": "Zapytania zakresowe (np. warunek z BETWEEN)",
      "correct": false
    },
    {
      "answer": "Zapytania zwracające pojedyncze wartości",
      "correct": false
    },
    {
      "answer": "Zapytania zawierające ORDER BY",
      "correct": false
    },
    {
      "answer": "Zapytania z użyciem LIKE",
      "correct": false
    }
  ],
  "id": "76f8dc19-d40e-4496-8ea7-32c2ceb75be4",
  "createdAt": 1657199812909
}
